Workbook

Sheet Read me
A1: PAMOJA simplified financial model - v0.1 (draft)
A2: How $24m flows TAMISEMI -> Lenders -> CMGs as loans, and back as repayments.
A5: HOW TO USE
A6: 1. Change the yellow cells with blue numbers only. Everything else is a formula.
A7: 2. Inputs: fund size and assumptions. Districts: CMG numbers, savings and loan size per LGA.
A8: 3. Fund flow: one annual cycle as a waterfall, with a check that the corpus is restored.
A9: 4. Monthly cycle: when loans go out and come back over 12 months.
A11: IMPORTANT
A12: - All district data and rates are DUMMY placeholders. Replace them with real figures.
A13: - The split of interest (default budget, discounts, TAMISEMI, region, LGA) is a first guess to confirm.
A15: SIMPLE LOGIC (v0.1)
A16: - Lending corpus = Total fund - Lender incentives - CMG incentives.
... A29: See the 'Glossary' sheet for all acronyms and terms.

Sheet Inputs
A1: Inputs
A2: Yellow cells are inputs. Dummy values - replace with agreed figures.
A4: Item | B4: Value | C4: Unit | D4: Note
A5: FUND
A6: Total PAMOJA fund | B6: 24000000 | C6: USD | D6: From TAMISEMI
A7: Lender incentives (set aside) | B7: 2000000 | C7: USD | D7: Not lent out
A8: CMG incentives (set aside) | B8: 2000000 | C8: USD | D8: Not lent out
A9: Lending corpus | B9: =B6-B7-B8 | C9: USD | D9: Formula: money available to lend
A10: LENDING RULES
A11: Maximum Loan:Savings ratio | B11: 0.5 | C11: x | D11: Loan must not exceed this x CMG savings
A12: Interest rate (flat, per year) | B12: 0.18 | C12: % | D12: Placeholder; must be at or below TAMISEMI ceiling
A13: Loan term | B13: 6 | C13: months | D13: Months. Must end before the CMG share-out
A14: Portfolio default rate (budget) | B14: 0.05 | C14: % | D14: % of principal lent that is not repaid
A15: SPLIT OF INTEREST COLLECTED
A16: Default budget (loss reserve) | B16: 0.3 | C16: % | D16: Returned to fund to cover defaults
A17: Lender discount | B17: 0.15 | C17: % | D17: Placeholder
A18: TAMISEMI share | B18: 0.1 | C18: % | D18: Placeholder
A19: Region share | B19: 0.05 | C19: % | D19: Placeholder
A20: LGA share | B20: 0.05 | C20: % | D20: Placeholder
A21: Lender net margin (remainder) | B21: =1-SUM(B16:B20) | C21: % | D21: Formula: what is left for the lender
A22: Check: split adds to 100% or less | B22: =IF(B21>=0,"OK","ERROR: over 100%")

Sheet Districts
A1: Allocation by district (LGA)
A2: Dummy data. Add real LGAs in the yellow cells; up to 20 rows.
A4: District (LGA) | B4: Number of CMGs | C4: Average savings per CMG (USD) | D4: Average loan asked per CMG (USD) | E4: Loan cap per CMG = savings x ratio | F4: Loan per CMG (smaller of the two) | G4: Loan:Savings ratio used | H4: Demand (USD) | I4: Allocation (USD) | J4: Share of corpus
A5: District A | B5: 2500 | C5: 4000 | D5: 2500 | E5: =IF(B5="","",C5*Inputs!$B$11) | F5: =IF(B5="","",MIN(D5,E5)) | G5: =IF(B5="","",F5/C5) | H5: =IF(B5="",0,B5*F5) | I5: =IF(B5="",0,H5*$B$28) | J5: =IF(B5="","",I5/Inputs!$B$9)
A6: District B | B6: 1800 | C6: 3000 | D6: 2000 | E6: =IF(B6="","",C6*Inputs!$B$11) | F6: =IF(B6="","",MIN(D6,E6)) | G6: =IF(B6="","",F6/C6) | H6: =IF(B6="",0,B6*F6) | I6: =IF(B6="",0,H6*$B$28) | J6: =IF(B6="","",I6/Inputs!$B$9)
A7: District C | B7: 3200 | C7: 5000 | D7: 3000 | E7: =IF(B7="","",C7*Inputs!$B$11) | F7: =IF(B7="","",MIN(D7,E7)) | G7: =IF(B7="","",F7/C7) | H7: =IF(B7="",0,B7*F7) | I7: =IF(B7="",0,H7*$B$28) | J7: =IF(B7="","",I7/Inputs!$B$9)
A8: District D | B8: 1500 | C8: 3500 | D8: 1500 | E8: =IF(B8="","",C8*Inputs!$B$11) | F8: =IF(B8="","",MIN(D8,E8)) | G8: =IF(B8="","",F8/C8) | H8: =IF(B8="",0,B8*F8) | I8: =IF(B8="",0,H8*$B$28) | J8: =IF(B8="","",I8/Inputs!$B$9)
A9: District E | B9: 2000 | C9: 4500 | D9: 2500 | E9: =IF(B9="","",C9*Inputs!$B$11) | F9: =IF(B9="","",MIN(D9,E9)) | G9: =IF(B9="","",F9/C9) | H9: =IF(B9="",0,B9*F9) | I9: =IF(B9="",0,H9*$B$28) | J9: =IF(B9="","",I9/Inputs!$B$9)
E10: =IF(B10="","",C10*Inputs!$B$11) | F10: =IF(B10="","",MIN(D10,E10)) | G10: =IF(B10="","",F10/C10) | H10: =IF(B10="",0,B10*F10) | I10: =IF(B10="",0,H10*$B$28) | J10: =IF(B10="","",I10/Inputs!$B$9)
E11: =IF(B11="","",C11*Inputs!$B$11) | F11: =IF(B11="","",MIN(D11,E11)) | G11: =IF(B11="","",F11/C11) | H11: =IF(B11="",0,B11*F11) | I11: =IF(B11="",0,H11*$B$28) | J11: =IF(B11="","",I11/Inputs!$B$9)
E12: =IF(B12="","",C12*Inputs!$B$11) | F12: =IF(B12="","",MIN(D12,E12)) | G12: =IF(B12="","",F12/C12) | H12: =IF(B12="",0,B12*F12) | I12: =IF(B12="",0,H12*$B$28) | J12: =IF(B12="","",I12/Inputs!$B$9)
E13: =IF(B13="","",C13*Inputs!$B$11) | F13: =IF(B13="","",MIN(D13,E13)) | G13: =IF(B13="","",F13/C13) | H13: =IF(B13="",0,B13*F13) | I13: =IF(B13="",0,H13*$B$28) | J13: =IF(B13="","",I13/Inputs!$B$9)
E14: =IF(B14="","",C14*Inputs!$B$11) | F14: =IF(B14="","",MIN(D14,E14)) | G14: =IF(B14="","",F14/C14) | H14: =IF(B14="",0,B14*F14) | I14: =IF(B14="",0,H14*$B$28) | J14: =IF(B14="","",I14/Inputs!$B$9)
E15: =IF(B15="","",C15*Inputs!$B$11) | F15: =IF(B15="","",MIN(D15,E15)) | G15: =IF(B15="","",F15/C15) | H15: =IF(B15="",0,B15*F15) | I15: =IF(B15="",0,H15*$B$28) | J15: =IF(B15="","",I15/Inputs!$B$9)
E16: =IF(B16="","",C16*Inputs!$B$11) | F16: =IF(B16="","",MIN(D16,E16)) | G16: =IF(B16="","",F16/C16) | H16: =IF(B16="",0,B16*F16) | I16: =IF(B16="",0,H16*$B$28) | J16: =IF(B16="","",I16/Inputs!$B$9)
E17: =IF(B17="","",C17*Inputs!$B$11) | F17: =IF(B17="","",MIN(D17,E17)) | G17: =IF(B17="","",F17/C17) | H17: =IF(B17="",0,B17*F17) | I17: =IF(B17="",0,H17*$B$28) | J17: =IF(B17="","",I17/Inputs!$B$9)
E18: =IF(B18="","",C18*Inputs!$B$11) | F18: =IF(B18="","",MIN(D18,E18)) | G18: =IF(B18="","",F18/C18) | H18: =IF(B18="",0,B18*F18) | I18: =IF(B18="",0,H18*$B$28) | J18: =IF(B18="","",I18/Inputs!$B$9)
E19: =IF(B19="","",C19*Inputs!$B$11) | F19: =IF(B19="","",MIN(D19,E19)) | G19: =IF(B19="","",F19/C19) | H19: =IF(B19="",0,B19*F19) | I19: =IF(B19="",0,H19*$B$28) | J19: =IF(B19="","",I19/Inputs!$B$9)
E20: =IF(B20="","",C20*Inputs!$B$11) | F20: =IF(B20="","",MIN(D20,E20)) | G20: =IF(B20="","",F20/C20) | H20: =IF(B20="",0,B20*F20) | I20: =IF(B20="",0,H20*$B$28) | J20: =IF(B20="","",I20/Inputs!$B$9)
E21: =IF(B21="","",C21*Inputs!$B$11) | F21: =IF(B21="","",MIN(D21,E21)) | G21: =IF(B21="","",F21/C21) | H21: =IF(B21="",0,B21*F21) | I21: =IF(B21="",0,H21*$B$28) | J21: =IF(B21="","",I21/Inputs!$B$9)
... E24: =IF(B24="","",C24*Inputs!$B$11) | F24: =IF(B24="","",MIN(D24,E24)) | G24: =IF(B24="","",F24/C24) | H24: =IF(B24="",0,B24*F24) | I24: =IF(B24="",0,H24*$B$28) | J24: =IF(B24="","",I24/Inputs!$B$9)
A25: TOTAL | B25: =SUM(B5:B24) | H25: =SUM(H5:H24) | I25: =SUM(I5:I24) | J25: =SUM(J5:J24)
A27: Lending corpus | B27: =Inputs!$B$9
A28: Scale factor (1 = full demand met) | B28: =IF(H25=0,0,MIN(1,B27/H25))
A29: Corpus not used | B29: =B27-I25
A30: Demand not met | B30: =H25-I25

Sheet Fund flow
A1: Fund flow for one annual cycle
A2: TAMISEMI -> Lenders -> CMGs -> back. All formulas.
A4: Step | B4: Amount (USD) | C4: From -> To | D4: How it is worked out
A5: 1. MONEY OUT
A6: Total PAMOJA fund | B6: =Inputs!B6 | C6: TAMISEMI
A7: Lender incentives set aside | B7: =Inputs!B7 | C7: TAMISEMI -> Lenders | D7: Paid later, not lent
A8: CMG incentives set aside | B8: =Inputs!B8 | C8: TAMISEMI -> CMGs | D8: Paid later, not lent
A9: Advance to lenders (= loans made) | B9: =Districts!$I$25 | C9: TAMISEMI -> Lenders | D9: Sum of district allocations
A10: Corpus not lent (returned) | B10: =Inputs!B9-B9 | C10: Lenders -> TAMISEMI | D10: Unused advance
A11: Loans to CMGs | B11: =B9 | C11: Lenders -> CMGs | D11: Advance lent in full
A12: 2. MONEY BACK FROM CMGs
A13: Principal defaulted | B13: =B11*Inputs!$B$14 | D13: Loans x default rate
A14: Principal repaid | B14: =B11-B13 | C14: CMGs -> Lenders | D14: Loans - defaults
A15: Interest collected | B15: =B14*Inputs!$B$12*Inputs!$B$13/12 | C15: CMGs -> Lenders | D15: Flat: repaid loans x rate x term/12
A16: Total repayments | B16: =B14+B15 | C16: CMGs -> Lenders
A17: 3. SPLIT OF INTEREST
A18: Default budget (loss reserve) | B18: =B15*Inputs!B16 | C18: Lenders -> TAMISEMI
A19: Lender discount | B19: =B15*Inputs!B17 | C19: Kept by lenders
A20: TAMISEMI share | B20: =B15*Inputs!B18 | C20: Lenders -> TAMISEMI
A21: Region share | B21: =B15*Inputs!B19 | C21: -> Region
A22: LGA share | B22: =B15*Inputs!B20 | C22: -> LGA
A23: Lender net margin | B23: =B15*Inputs!B21 | C23: Kept by lenders | D23: Remainder
A24: 4. CORPUS CHECK (end of cycle)
A25: Corpus at start | B25: =Inputs!B9
A26: Principal repaid to TAMISEMI | B26: =B14 | C26: Lenders -> TAMISEMI
A27: Corpus not lent | B27: =B10
A28: Default budget added back | B28: =B18 | D28: Covers the defaulted principal
A29: Corpus at end | B29: =B26+B27+B28
A30: Gap (end - start) | B30: =B29-B25 | D30: Negative = corpus NOT restored
A31: Result | B31: =IF(B30>=-0.5,"Corpus restored","Corpus NOT restored - raise interest share for defaults or rate")
A32: Default budget needed (% of interest) | B32: =IF(B15=0,0,B13/B15) | D32: Minimum share of interest to cover defaults
A33: Break-even default rate | B33: =Inputs!B16*Inputs!$B$12*Inputs!$B$13/12/(1+Inputs!B16*Inputs!$B$12*Inputs!$B$13/12) | D33: Highest default rate the current split can cover

Sheet Monthly cycle
A1: Monthly cycle (12 months)
A2: Enter the % of total loans disbursed each month (yellow). Repayments are equal monthly instalments over the loan term.
A4: Line | B4: M1 | C4: M2 | D4: M3 | E4: M4 | F4: M5 | G4: M6 | H4: M7 | I4: M8 | J4: M9 | K4: M10 | L4: M11 | M4: M12 | N4: Total
A5: Month number | B5: 1 | C5: 2 | D5: 3 | E5: 4 | F5: 5 | G5: 6 | H5: 7 | I5: 8 | J5: 9 | K5: 10 | L5: 11 | M5: 12
A6: % of loans disbursed this month | B6: 0.4 | C6: 0.3 | D6: 0.2 | E6: 0.1 | F6: 0 | G6: 0 | H6: 0 | I6: 0 | J6: 0 | K6: 0 | L6: 0 | M6: 0 | N6: =SUM(B6:M6)
A7: Loans disbursed | B7: =B6*Districts!$I$25 | C7: =C6*Districts!$I$25 | D7: =D6*Districts!$I$25 | E7: =E6*Districts!$I$25 | F7: =F6*Districts!$I$25 | G7: =G6*Districts!$I$25 | H7: =H6*Districts!$I$25 | I7: =I6*Districts!$I$25 | ... M7: =M6*Districts!$I$25 | N7: =SUM(B7:M7)
A8: Principal due | B8: =SUMPRODUCT((B$5-$B$5:$M$5>=1)*(B$5-$B$5:$M$5<=Inputs!$B$13)*$B$7:$M$7)/Inputs!$B$13 | C8: =SUMPRODUCT((C$5-$B$5:$M$5>=1)*(C$5-$B$5:$M$5<=Inputs!$B$13)*$B$7:$M$7)/Inputs!$B$13 | D8: =SUMPRODUCT((D$5-$B$5:$M$5>=1)*(D$5-$B$5:$M$5<=Inputs!$B$13)*$B$7:$M$7)/Inputs!$B$13 | E8: =SUMPRODUCT((E$5-$B$5:$M$5>=1)*(E$5-$B$5:$M$5<=Inputs!$B$13)*$B$7:$M$7)/Inputs!$B$13 | F8: =SUMPRODUCT((F$5-$B$5:$M$5>=1)*(F$5-$B$5:$M$5<=Inputs!$B$13)*$B$7:$M$7)/Inputs!$B$13 | G8: =SUMPRODUCT((G$5-$B$5:$M$5>=1)*(G$5-$B$5:$M$5<=Inputs!$B$13)*$B$7:$M$7)/Inputs!$B$13 | H8: =SUMPRODUCT((H$5-$B$5:$M$5>=1)*(H$5-$B$5:$M$5<=Inputs!$B$13)*$B$7:$M$7)/Inputs!$B$13 | I8: =SUMPRODUCT((I$5-$B$5:$M$5>=1)*(I$5-$B$5:$M$5<=Inputs!$B$13)*$B$7:$M$7)/Inputs!$B$13 | ... M8: =SUMPRODUCT((M$5-$B$5:$M$5>=1)*(M$5-$B$5:$M$5<=Inputs!$B$13)*$B$7:$M$7)/Inputs!$B$13 | N8: =SUM(B8:M8)
A9: Principal repaid (after defaults) | B9: =B8*(1-Inputs!$B$14) | C9: =C8*(1-Inputs!$B$14) | D9: =D8*(1-Inputs!$B$14) | E9: =E8*(1-Inputs!$B$14) | F9: =F8*(1-Inputs!$B$14) | G9: =G8*(1-Inputs!$B$14) | H9: =H8*(1-Inputs!$B$14) | I9: =I8*(1-Inputs!$B$14) | ... M9: =M8*(1-Inputs!$B$14) | N9: =SUM(B9:M9)
A10: Interest collected | B10: =B9*Inputs!$B$12/12*Inputs!$B$13 | C10: =C9*Inputs!$B$12/12*Inputs!$B$13 | D10: =D9*Inputs!$B$12/12*Inputs!$B$13 | E10: =E9*Inputs!$B$12/12*Inputs!$B$13 | F10: =F9*Inputs!$B$12/12*Inputs!$B$13 | G10: =G9*Inputs!$B$12/12*Inputs!$B$13 | H10: =H9*Inputs!$B$12/12*Inputs!$B$13 | I10: =I9*Inputs!$B$12/12*Inputs!$B$13 | ... M10: =M9*Inputs!$B$12/12*Inputs!$B$13 | N10: =SUM(B10:M10)
A11: Loans outstanding (end of month) | B11: =0+B7-B8 | C11: =B11+C7-C8 | D11: =C11+D7-D8 | E11: =D11+E7-E8 | F11: =E11+F7-F8 | G11: =F11+G7-G8 | H11: =G11+H7-H8 | I11: =H11+I7-I8 | J11: =I11+J7-J8 | ... M11: =L11+M7-M8
A12: Fund cash on hand (end of month) | B12: =Inputs!$B$9-B7+B9+B10*Inputs!$B$16 | C12: =B12-C7+C9+C10*Inputs!$B$16 | D12: =C12-D7+D9+D10*Inputs!$B$16 | E12: =D12-E7+E9+E10*Inputs!$B$16 | F12: =E12-F7+F9+F10*Inputs!$B$16 | G12: =F12-G7+G9+G10*Inputs!$B$16 | H12: =G12-H7+H9+H10*Inputs!$B$16 | I12: =H12-I7+I9+I10*Inputs!$B$16 | J12: =I12-J7+J9+J10*Inputs!$B$16 | ... M12: =L12-M7+M9+M10*Inputs!$B$16
A13: Warning: loan still running after month 12 | B13: =IF(SUMPRODUCT(($B$5:$M$5+Inputs!$B$13>12)*($B$7:$M$7))>0,"YES - some loans end after the cycle. Move disbursement earlier or shorten the term.","No - all loans end within the cycle")
A15: Latest month a loan can go out and still be repaid by month 12: | B15: =12-Inputs!$B$13
A16: Cash on hand at end of month 12 (should equal the corpus if restored): | B16: =M12
A17: Check: % disbursed adds to 100% | B17: =IF(ABS(N6-1)<0.0001,"OK","ERROR: adjust row 6")
A19: Note: Fund cash counts principal repaid plus the default budget share of interest. Other interest shares go to lenders, TAMISEMI, region and LGA.

Sheet Glossary
A1: Glossary
A2: Acronyms and terms used in this model.
A4: Term | B4: Meaning
A5: Advance | B5: Money TAMISEMI sends a lender ahead of lending, based on the CMG pool allocated to that lender.
A6: Allocation | B6: The share of the lending corpus given to a district, based on its loan demand.
A7: Annual cycle | B7: The CMG's savings year. Loans must be repaid before the share-out at the end.
A8: Break-even default rate | B8: The highest default rate the default budget can cover and still restore the corpus.
A9: CMG | B9: Community Microfinance Group: a savings group whose members save and lend to each other.
A10: Corpus | B10: The pool of money available to lend ($24m less the $4m set aside for incentives).
A11: Default | B11: A loan, or part of a loan, that is not repaid.
A12: Default budget / loss reserve | B12: The share of interest set aside to cover defaults.
A13: Demand | B13: Number of CMGs x loan per CMG, before any scaling down.
A14: Discount | B14: A share of interest given back or kept to reward a party (e.g. lender discount).
A15: Flat interest | B15: Interest worked out on the full loan amount for the whole term, not on the falling balance.
... A25: TZS / USD | B25: Tanzanian shilling / United States dollar.
